elias_ollama/__init__.py
elias_ollama/cli.py
elias_ollama/ollama_client.py
elias_ollama-0.2.0.dist-info/METADATA
elias_ollama-0.2.0.dist-info/WHEEL
elias_ollama-0.2.0.dist-info/entry_points.txt
elias_ollama-0.2.0.dist-info/top_level.txt
elias_ollama-0.2.0.dist-info/RECORD
