Metadata-Version: 2.4
Name: elias_ollama
Version: 0.2.0
Summary: 一个用于调用Ollama模型的Python工具包
Home-page: https://github.com/tenbj/elias_ollama
Author: Elias Liu
Author-email: elias.liu120@gmail.com
Classifier: Programming Language :: Python :: 3
Classifier: License :: OSI Approved :: MIT License
Classifier: Operating System :: OS Independent
Requires-Python: >=3.6
Requires-Dist: requests>=2.25.0
Dynamic: author
Dynamic: author-email
Dynamic: classifier
Dynamic: description
Dynamic: description-content-type
Dynamic: home-page
Dynamic: requires-dist
Dynamic: requires-python
Dynamic: summary
